{"container_type": "Publication", "source": "PUBLICATION_SEARCH_SNIPPET", "bib": {"title": "Intrusion detection systems", "author": "Bace, Rebecca Gurley and Mell, Peter and others", "pub_year": "2001", "venue": "NA", "abstract": "Intrusion detection systems (IDSs) are software or hardware systems that automate the process of monitoring the events occurring in a computer system or network, analyzing them", "publisher": "US Department of Commerce, Technology Administration, National Institute of~\u2026", "pub_type": "misc", "bib_id": "bace2001intrusion"}, "filled": true, "gsrank": 1, "pub_url": "http://cs.uccs.edu/~cchow/pub/ids/NISTsp800-31.pdf", "author_id": ["", "FoFadTEAAAAJ"], "url_scholarbib": "/scholar?q=info:dCHcAPIVDhUJ:scholar.google.com/&output=cite&scirp=0&hl=en", "url_add_sclib": "/citations?hl=en&xsrf=&continue=/scholar%3Fq%3DIntrusion%2Bdetection%2Bsystems%26hl%3Den%26as_sdt%3D0,5&citilm=1&update_op=library_add&info=dCHcAPIVDhUJ&ei=6ZSgYYSlDoGEmgGSwISoAw&json=", "num_citations": 546, "citedby_url": "/scholar?cites=1517174253611131252&as_sdt=2005&sciodt=0,5&hl=en", "url_related_articles": "/scholar?q=related:dCHcAPIVDhUJ:scholar.google.com/&scioq=Intrusion+detection+systems&hl=en&as_sdt=0,5", "eprint_url": "http://cs.uccs.edu/~cchow/pub/ids/NISTsp800-31.pdf"}